pyfix_imports-0.7.2.dist-info/METADATA
pyfix_imports-0.7.2.dist-info/WHEEL
pyfix_imports-0.7.2.dist-info/entry_points.txt
pyfix_imports-0.7.2.dist-info/licenses/LICENSE
pyfix_imports/__init__.py
pyfix_imports/__main__.py
pyfix_imports/commandline/__init__.py
pyfix_imports/commandline/cli.py
pyfix_imports/config.py
pyfix_imports/file.py
pyfix_imports/fix_code.py
pyfix_imports/package.py
pyfix_imports/predefined.py
pyfix_imports/pyflake.py
pyfix_imports-0.7.2.dist-info/RECORD
