Metadata-Version: 2.1
Name: pyfix-imports
Version: 0.7.2
Summary: python tool that will fix your missing imports
Author-Email: Rishabh <jharishabh672003@gmail.com>
License: GPL-3.0-only
Requires-Python: >=3.11
Requires-Dist: click>=8.1.7
Requires-Dist: pyflakes>=3.2.0
Requires-Dist: importlib>=1.0.4
Requires-Dist: xdg-base-dirs>=6.0.1
